allcities/__init__.py
allcities/__main__.py
allcities/city.py
allcities/cityset.py
allcities/core.py
allcities/data/cities1000.pickle.gz
allcities/data/last_update
allcities-1.0.3.dist-info/LICENSE.md
allcities-1.0.3.dist-info/METADATA
allcities-1.0.3.dist-info/WHEEL
allcities-1.0.3.dist-info/top_level.txt
allcities-1.0.3.dist-info/RECORD
