Metadata-Version: 2.1
Name: allcities
Version: 1.0.3
Summary: allcities - Python library to access all the cities of the world with a population of at least 1000 inhabitants.
Home-page: https://github.com/Jonchun/allcities
Author: Jonathan Chun
Author-email: git@jonathanchun.com
License: MIT
Platform: UNKNOWN
Classifier: Programming Language :: Python :: 3
Classifier: License :: OSI Approved :: MIT License
Classifier: Operating System :: OS Independent
Requires-Dist: requests
